MANIFEST.in
README.txt
setup.cfg
setup.py
docs/HISTORY.txt
docs/INSTALL.txt
docs/LICENSE.GPL
docs/LICENSE.txt
jalon/__init__.py
jalon.wowza.egg-info/PKG-INFO
jalon.wowza.egg-info/SOURCES.txt
jalon.wowza.egg-info/dependency_links.txt
jalon.wowza.egg-info/entry_points.txt
jalon.wowza.egg-info/namespace_packages.txt
jalon.wowza.egg-info/not-zip-safe
jalon.wowza.egg-info/paster_plugins.txt
jalon.wowza.egg-info/requires.txt
jalon.wowza.egg-info/top_level.txt
jalon/wowza/__init__.py
jalon/wowza/configure.zcml
jalon/wowza/skins.zcml
jalon/wowza/tests.py
jalon/wowza/content/__init__.py
jalon/wowza/content/configure.zcml
jalon/wowza/content/interfaces.py
jalon/wowza/content/jalonwowza.py
jalon/wowza/profiles/default/componentregistry.xml
jalon/wowza/profiles/default/metadata.xml
jalon/wowza/profiles/default/skins.xml
jalon/wowza/profiles/default/toolset.xml
jalon/wowza/skins/jalon_wowza/ask_streaming.pt
jalon/wowza/skins/jalon_wowza/ask_streaming_script.py
jalon/wowza/skins/jalon_wowza/forbid_streaming.pt
jalon/wowza/skins/jalon_wowza/macro_gestion_wowza.pt
jalon/wowza/skins/jalon_wowza/modify_streaming.pt
jalon/wowza/skins/jalon_wowza/modify_streaming_script.py
jalon/wowza/skins/jalon_wowza/saveConfigWowza.py