Metadata-Version: 1.1
Name: jalon.wowza
Version: 1.0
Summary: UNKNOWN
Home-page: http://svn.plone.org/svn/collective/
Author: Bordonado Christophe (Université Nice Sophia Antipolis Service TICE)
Author-email: pi@unice.fr
License: GPL
Platform: UNKNOWN
Classifier: Framework :: Plone
Classifier: Programming Language :: Python
